sigmapy/__init__.py
sigmapy/normal.py
sigmapy/sigma_sets.py
sigmapy/sigma_transform.py
sigmapy-0.1.dist-info/LICENSE
sigmapy-0.1.dist-info/METADATA
sigmapy-0.1.dist-info/WHEEL
sigmapy-0.1.dist-info/top_level.txt
sigmapy-0.1.dist-info/RECORD
